ZEN_norm/.gitignore
ZEN_norm/__init__.py
ZEN_norm/chrom_analysis.py
ZEN_norm/compare_norm.py
ZEN_norm/reverse_norm.py
ZEN_norm/zone_norm.py
zen_norm-0.0.1.dist-info/METADATA
zen_norm-0.0.1.dist-info/WHEEL
zen_norm-0.0.1.dist-info/licenses/LICENSE
zen_norm-0.0.1.dist-info/RECORD
