Metadata-Version: 2.4
Name: ZEN-norm
Version: 0.0.1
Summary: Zone Equalisation Normalisation: A Python package for bigWig scaling
Project-URL: Repository, https://github.com/Genome-Function-Initiative-Oxford/Zone-Equalisation-Normalisation
Project-URL: Issues, https://github.com/Genome-Function-Initiative-Oxford/ZEN-norm/issues
Author-email: Tom Wilson <tw556@cantab.ac.uk>
License: MIT
License-File: LICENSE
Keywords: atac-seq,bigwig,bioinformatics,chip-seq,genetics,genomics,normalisation,tt-seq
Classifier: Development Status :: 2 - Pre-Alpha
Classifier: Intended Audience :: Science/Research
Classifier: License :: OSI Approved :: MIT License
Classifier: Natural Language :: English
Classifier: Operating System :: MacOS
Classifier: Operating System :: POSIX
Classifier: Operating System :: Unix
Classifier: Programming Language :: Python :: 3
Classifier: Programming Language :: Python :: 3.10
Classifier: Programming Language :: Python :: 3.11
Classifier: Programming Language :: Python :: 3.12
Classifier: Topic :: Scientific/Engineering :: Bio-Informatics
Requires-Python: >=3.10
Requires-Dist: deeptools==3.5.6
Requires-Dist: matplotlib>=3.10
Requires-Dist: numba>=0.61
Requires-Dist: numpy>=2.2
Requires-Dist: pandas>=2.3
Requires-Dist: pybigwig==0.3.24
Requires-Dist: scipy>=1.15
Requires-Dist: seaborn>=0.13
Requires-Dist: sympy>=1.14
